step_parser/__init__.py
step_parser/cli.py
step_parser/constants.py
step_parser/step_patterns.py
step_parser/stepchart.py
step_parser/time_calculations.py
sm_tools-0.0.3.dist-info/METADATA
sm_tools-0.0.3.dist-info/WHEEL
sm_tools-0.0.3.dist-info/entry_points.txt
sm_tools-0.0.3.dist-info/top_level.txt
sm_tools-0.0.3.dist-info/RECORD
