Metadata-Version: 2.1
Name: sm-tools
Version: 0.0.3
Summary: StepMania tools
Home-page: https://github.com/JaceTSM/sm_tools
Author: Tim Murphy
Author-email: jac3tssm@gmail.com
License: UNKNOWN
Platform: UNKNOWN
Classifier: Programming Language :: Python :: 3
Classifier: License :: OSI Approved :: MIT License
Classifier: Operating System :: OS Independent
Requires-Python: >=3.6
Requires-Dist: pandas
